MANIFEST.in
setup.py
mycommute/__init__.py
mycommute/plotting_functions.py
mycommute.egg-info/PKG-INFO
mycommute.egg-info/SOURCES.txt
mycommute.egg-info/dependency_links.txt
mycommute.egg-info/not-zip-safe
mycommute.egg-info/requires.txt
mycommute.egg-info/top_level.txt