Metadata-Version: 1.0
Name: mycommute
Version: 0.1
Summary: Analyse my London commuting
Home-page: http://github.com/ppuggioni/mycommute
Author: Paolo Puggioni
Author-email: p.paolo321@gmail.com
License: Apache2.0
Platform: UNKNOWN
